{
    "text": {
        "merger": "يس والقران الحكيم انك لمن المرسلين صراط مستقيم تنزيل العزيز الرحيم لتنذر قوما انذر اباؤهم فهم غفلون لقد حق القول اكثرهم فهم لا يؤمنون انا جعلنا اعناقهم اغللا فهي الى الاذقان فهم مقمحون وجعلنا بين ايديهم سدا ومن خلفهم سدا فاغشينهم فهم لا يبصرون وسواء عليهم ءانذرتهم ام تنذرهم لا يؤمنون انما تنذر اتبع الذكر وخشي الرحمن بالغيب فبشره بمغفرة واجر كريم انا نحن نحي الموتى ونكتب قدموا واثارهم وكل شيء احصينه امام مبين واضرب لهم مثلا اصحب القرية اذ جاءها المرسلون اذ ارسلنا اليهم اثنين فكذبوهما فعززنا بثالث فقالوا انا اليكم مرسلون قالوا انتم الا بشر مثلنا وما انزل الرحمن شيء ان انتم الا تكذبون قالوا ربنا يعلم انا اليكم لمرسلون وما علينا الا البلغ المبين قالوا انا تطيرنا بكم لىن تنتهوا لنرجمنكم وليمسنكم منا عذاب اليم قالوا طاىركم معكم اىن ذكرتم بل انتم قوم مسرفون وجاء اقصا المدينة رجل يسعى قال يقوم اتبعوا المرسلين اتبعوا لا يسـلكم اجرا وهم مهتدون وما لي لا اعبد فطرني واليه ترجعون ءاتخذ دونه الهة ان يردن الرحمن بضر لا تغن عني شفاعتهم شيـا ولا ينقذون اني اذا لفي ضلل مبين اني امنت بربكم فاسمعون قيل ادخل الجنة قال يليت قومي يعلمون بما غفر لي ربي وجعلني المكرمين وما انزلنا قومه بعده جند السماء وما كنا منزلين ان كانت الا صيحة واحدة فاذا خامدون يحسرة العباد يأتيهم رسول الا كانوا به يستهزءون الم يروا كم اهلكنا قبلهم القرون انهم اليهم لا يرجعون وان لما جميع لدينا محضرون واية لهم الارض الميتة احيينها واخرجنا منها حبا فمنه يأكلون وجعلنا فيها جنت نخيل واعناب وفجرنا فيها العيون ليأكلوا ثمره وما عملته ايديهم افلا يشكرون سبحن خلق الازواج كلها مما تنبت الارض ومن انفسهم ومما لا يعلمون واية لهم اليل نسلخ منه النهار فاذا مظلمون والشمس تجري لمستقر لها تقدير العزيز العليم والقمر قدرنه منازل حتى عاد كالعرجون القديم لا الشمس ينبغي لها ان تدرك القمر ولا اليل سابق النهار وكل فلك يسبحون واية لهم انا حملنا ذريتهم فى الفلك المشحون وخلقنا لهم مثله يركبون وان نشأ نغرقهم فلا صريخ لهم ولاهم ينقذون الا رحمة منا ومتاعا الى حين واذا قيل لهم اتقوا بين ايديكم وما خلفكم لعلكم ترحمون وما تأتيهم اية ايت ربهم الا كانوا عنها معرضين واذا قيل لهم انفقوا مما رزقكم الله قال الذين كفروا للذين امنوا انطعم لو يشاء الله اطعمه ان انتم الا ضلل مبين ويقولون متى الوعد ان كنتم صدقين ينظرون الا صيحة واحدة تأخذهم وهم يخصمون فلا يستطيعون توصية ولا الى اهلهم يرجعون ونفخ فى الصور فاذا الاجداث الى ربهم ينسلون قالوا يويلنا بعثنا مرقدنا وعد الرحمن وصدق المرسلون ان كانت الا صيحة واحدة فاذا جميع لدينا محضرون فاليوم لا تظلم نفس شيـا ولا تجزون الا كنتم تعملون ان اصحب الجنة اليوم شغل فكهون وازواجهم ظلل الاراىك متكـون لهم فيها فاكهة ولهم يدعون سلم قولا رب رحيم وامتازوا اليوم ايها المجرمون الم اعهد اليكم يبني ادم ان لا تعبدوا الشيطن انه لكم عدو مبين وان اعبدوني صراط مستقيم ولقد اضل منكم جبلا كثيرا افلم تكونوا تعقلون جهنم كنتم توعدون اصلوها اليوم بما كنتم تكفرون اليوم نختم افواههم وتكلمنا ايديهم وتشهد ارجلهم بما كانوا يكسبون ولو نشاء لطمسنا اعينهم فاستبقوا الصراط فانى يبصرون ولو نشاء لمسخنهم مكانتهم فما استطاعوا مضيا ولا يرجعون ومن نعمره ننكسه فى الخلق افلا يعقلون وما علمنه الشعر وما ينبغي له ان الا ذكر وقران مبين لينذر حيا ويحق القول الكفرين اولم يروا انا خلقنا لهم مما عملت ايدينا انعاما فهم لها مالكون وذللنها لهم فمنها ركوبهم ومنها يأكلون ولهم فيها منافع ومشارب افلا يشكرون واتخذوا دون الله الهة لعلهم ينصرون لا يستطيعون نصرهم وهم لهم جند محضرون فلا يحزنك قولهم انا نعلم يسرون وما يعلنون اولم ير الانسان انا خلقنه نطفة فاذا خصيم مبين وضرب لنا مثلا ونسي خلقه قال يحي العظام وهي رميم قل يحييها انشاها اول مرة وهو بكل خلق عليم جعل لكم الشجر الاخضر نارا فاذا انتم منه توقدون اوليس خلق السموت والارض بقدر ان يخلق مثلهم بلى وهو الخلق العليم انما امره اذا اراد شيـا ان يقول له كن فيكون فسبحن بيده ملكوت شيء واليه ترجعون",
        "top_frequencies": {
            "top_5": [
                [
                    "لا",
                    12
                ],
                [
                    "لهم",
                    12
                ],
                [
                    "الا",
                    12
                ],
                [
                    "ان",
                    12
                ],
                [
                    "وما",
                    11
                ]
            ],
            "top_10": [
                [
                    "لا",
                    12
                ],
                [
                    "لهم",
                    12
                ],
                [
                    "الا",
                    12
                ],
                [
                    "ان",
                    12
                ],
                [
                    "وما",
                    11
                ],
                [
                    "انا",
                    9
                ],
                [
                    "مبين",
                    6
                ],
                [
                    "فاذا",
                    6
                ],
                [
                    "فهم",
                    5
                ],
                [
                    "قالوا",
                    5
                ]
            ],
            "top_15": [
                [
                    "لا",
                    12
                ],
                [
                    "لهم",
                    12
                ],
                [
                    "الا",
                    12
                ],
                [
                    "ان",
                    12
                ],
                [
                    "وما",
                    11
                ],
                [
                    "انا",
                    9
                ],
                [
                    "مبين",
                    6
                ],
                [
                    "فاذا",
                    6
                ],
                [
                    "فهم",
                    5
                ],
                [
                    "قالوا",
                    5
                ],
                [
                    "انتم",
                    5
                ],
                [
                    "ولا",
                    5
                ],
                [
                    "الى",
                    4
                ],
                [
                    "الرحمن",
                    4
                ],
                [
                    "قال",
                    4
                ]
            ]
        }
    },
    "translations": {
        "merger": "ya sin alquran penuh hikmah sungguh engkau muhammad salah rasulrasul jalan lurus wahyu diturunkan allah mahaperkasa maha penyayang engkau peringatan kaum nenek moyangnya peringatan lalai sungguh berlaku perkataan hukuman kebanyakan beriman sungguh memasang belenggu leher tangan diangkat dagu tertengadah jadikan hadapan sekat dinding sekat tutup mata engkau peringatan engkau peringatan beriman sesungguhnya engkau peringatan orangorang mengikuti peringatan takut tuhan maha pengasih berilah kabar gembira ampunan pahala mulia sungguh menghidupkan orangorang mati mencatat kerjakan bekasbekas tinggalkan kumpulkan kitab lauh mahfuzh buatlah perumpamaan penduduk negeri utusanutusan mengutus orang utusan mendustakan kuatkan utusan ketiga ketiga utusan sungguh orangorang diutus kepadamu penduduk negeri manusia allah maha pengasih menurunkan pendusta belaka tuhan sesungguhnya utusanutusannya kewajiban perintah allah sesungguhnya bernasib malang sungguh berhenti menyeru niscaya rajam merasakan siksaan pedih utusanutusan kemalangan peringatan kaum melampaui batas datanglah ujung kota lakilaki bergegas kaumku ikutilah utusanutusan ikutilah orang imbalan kepadamu orangorang petunjuk alasan bagiku menyembah allah menciptakanku kepadanyalah dikembalikan menyembah tuhantuhan selainnya allah maha pengasih bencana terhadapku pertolongan berguna diriku menyelamatkanku sesungguhnya berbuat kesesatan nyata sesungguhnya beriman tuhanmu dengarkanlah pengakuan keimananku masuklah surga lakilaki alangkah baiknya kaumku menyebabkan tuhanku ampun kepadaku menjadikan orangorang dimuliakan meninggal menurunkan pasukan langit kaumnya menurunkannya siksaan teriakan mati alangkah penyesalan hambahamba rasul memperolokolokkannya umatumat binasakan orangorang binasakan umat dihadapkan tanda kebesaran allah bumi mati tandus hidupkan bumi keluarkan darinya bijibijian bijibijian makan jadikan bumi kebunkebun kurma anggur pancarkan mata air makan buahnya hasil usaha tangan bersyukur mahasuci allah menciptakan berpasangpasangan ditumbuhkan bumi ketahui tanda kebesaran allah malam tanggalkan siang malam kegelapan matahari berjalan peredarannya ketetapan allah mahaperkasa maha tetapkan peredaran peredaran kembalilah bentuk tandan tua matahari mengejar malam mendahului siang masingmasing beredar garis edarnya tanda kebesaran allah angkut keturunan kapal penuh muatan ciptakan angkutan kendarai tenggelamkan penolong diselamatkan selamatkan rahmat kesenangan hidup takutlah siksa hadapanmu dunia azab akhirat rahmat kali tanda tandatanda kebesaran tuhan berpaling darinya infakkanlah rezeki allah kepadamu orangorang kafir orangorang beriman makan orangorang allah memberinya makan benarbenar kesesatan nyata orangorang kafir janji berbangkit orang menunggu teriakan membinasakan bertengkar wasiat keluarganya ditiuplah sangkakala kuburnya hidup tuhannya celakalah membangkitkan tidur kubur dijanjikan allah maha pengasih rasulrasulnya teriakan dihadapkan dihisab dirugikan balasan kecuali sesuai kerjakan sesungguhnya penghuni surga bersenangsenang kesibukan pasanganpasangannya teduh bersandar dipandipan surga memperoleh buahbuahan memperoleh salam ucapan selamat tuhan maha penyayang orangorang kafir berpisahlah orangorang mukmin orangorang berdosa memerintahkan kepadamu anak cucu adam menyembah setan sungguh setan musuh nyata menyembahku jalan lurus sungguh setan menyesatkan mengerti neraka jahanam diperingatkan kepadamu masuklah dalamnya mengingkarinya tutup mulut tangan kaki kesaksian kerjakan hapuskan penglihatan mata berlombalomba mencari jalan ubah bentuk sanggup berjalan sanggup barangsiapa panjangkan umurnya niscaya kembalikan kejadiannya mengerti mengajarkan syair muhammad bersyair baginya alquran pelajaran kitab muhammad peringatan orangorang hidup hatinya ketetapan azab orangorang kafir menciptakan hewan ternak ciptakan kekuasaan menguasainya menundukkannya hewanhewan sebagiannya tunggangan makan memperoleh manfaat minuman darinya bersyukur mengambil sesembahan allah pertolongan sesembahan menolong tentara disiapkan menjaga sesembahan ucapan engkau muhammad bersedih hati sungguh rahasiakan nyatakan manusia memperhatikan menciptakannya setetes mani musuh nyata perumpamaan melupakan kejadiannya menghidupkan tulangbelulang hancur luluh muhammad menghidupkannya allah menciptakannya kali maha makhluk allah menjadikan api untukmu kayu hijau nyalakan api kayu allah menciptakan langit bumi menciptakan jasad hancur maha pencipta maha sesungguhnya urusannya mahasuci allah tangannya kekuasaan dikembalikan",
        "top_frequencies": {
            "top_5": [
                [
                    "allah",
                    18
                ],
                [
                    "orangorang",
                    15
                ],
                [
                    "maha",
                    10
                ],
                [
                    "sungguh",
                    9
                ],
                [
                    "peringatan",
                    8
                ]
            ],
            "top_10": [
                [
                    "allah",
                    18
                ],
                [
                    "orangorang",
                    15
                ],
                [
                    "maha",
                    10
                ],
                [
                    "sungguh",
                    9
                ],
                [
                    "peringatan",
                    8
                ],
                [
                    "sesungguhnya",
                    7
                ],
                [
                    "engkau",
                    6
                ],
                [
                    "muhammad",
                    5
                ],
                [
                    "kepadamu",
                    5
                ],
                [
                    "bumi",
                    5
                ]
            ],
            "top_15": [
                [
                    "allah",
                    18
                ],
                [
                    "orangorang",
                    15
                ],
                [
                    "maha",
                    10
                ],
                [
                    "sungguh",
                    9
                ],
                [
                    "peringatan",
                    8
                ],
                [
                    "sesungguhnya",
                    7
                ],
                [
                    "engkau",
                    6
                ],
                [
                    "muhammad",
                    5
                ],
                [
                    "kepadamu",
                    5
                ],
                [
                    "bumi",
                    5
                ],
                [
                    "makan",
                    5
                ],
                [
                    "beriman",
                    4
                ],
                [
                    "tuhan",
                    4
                ],
                [
                    "pengasih",
                    4
                ],
                [
                    "nyata",
                    4
                ]
            ]
        }
    },
    "tafsir": {
        "merger": "surahsurah dibicarakan surah hurufhuruf abjad kesimpulannya pendapat terkuat menetapkan hurufhuruf abjad peringatan membangkitkan minat orang membacanya halhal ayatayat riwayat ibnu abbas diperoleh keterangan ya sin bermakna ya insan manusia muhammad pendapat abu hurairah ikrimah adhahhak sufyan bin uyainah said bin jubair ya sin berasal logat habsyah malik meriwayatkan zaid bin aslam arti ya sin kependekan namanama allah berpendapat ya sin ringkasan kalimat ya sayidal basyar nabi muhammad salah nama alquran mayoritas ulama menyerahkan arti ya sin allah lihat tafsir surah albaqarah2 1 allah bersumpah alquran penuh hikmah arti hikmah disarikan pendapatpendapat ahli tafsir hikmah muhkam benarnya dalamnya batil makna lafadh tujuan hikmah kisah hukumnya lainlain ditinjau segi hakim sifat dimiliki orang berakal cerdas halnya alquran hikmah dikandungnya bekal kehidupan manusia menyucikan hati kepuasan rohani kesucian hati kejernihan pikiran terbuka rahasiarahasia terkandung alam alquran bimbingan hidup penuh kebijaksanaan ajarannya sejalan harmonis pikiran sehat kehendak nafsu terkendali jalan pikiran arah kemaslahatan manusia ayat tujuan sumpah allah alquran mengandung hikmah pernyataan nabi muhammad salah rasul allah diutus membawa kebenaran penolakan orangorang memercayai muhammad rasul allah ayat rasulullah jalan lurus penegasan agama syariat dibawa nabi muhammad lurus berasal allah salah ciri risalah muhammad jalan lurus kebenaran dibawanya mencampuradukkan kebenaran kebatilan syariat muhammad saw cenderung mengikuti hawa nafsu manusiawi senantiasa mendorong manusia kebahagiaan dunia akhirat firman allah sungguh engkau benarbenar membimbing manusia jalan lurus asysyura42 52 ayat menentukan kedudukan alquran kitab suci berasal allah kitab suci hasil karangan manusia allah hambanya memahami hakikat kitab suci diturunkannya zat maha perkasa bertindak dikehendakinya maha penyayang hambanya kasih sayang tertuang alquran mengandung rahmat manusia arti ayat sungguh alquran benarbenar diturunkan tuhan alam asysyuara26 192 hikmah penurunan alquran peringatan bangsa arab diutus rasul ayat kerusakan moral bangsa arab akibat sifat lalai hati hati lalai hati melaksanakan kewajiban dilaksanakan bangsa arab keturunan nabi ismail dikirim rasul mengenal syariat membawa manusia kebahagiaan hidup dunia akhirat qaum mengandung pengertian khusus bangsa arab mengubah maksud risalah manusia ayat muhammad manusia sesungguhnya utusan allah alaraf7 158 ketetapan allah mengazab nenek moyang orangorang kafir kebanyakan umat menolak kedatangan rasul diutus keingkaran kejahatan akhlak menyebabkan hati menghayati kebenaran tunduk allah perumpamaan orangorang beriman seolaholah belenggu dipasang leher tangan diangkat dagu menyebabkan muka tertengadah gambaran orang beriman menoleh kanan kiri mengambil perbandingan belenggu erat kepalanya bergerak ayat keterangan seandainya kebenaran menuruti binasalah langit bumi dalamnya peringatan berpaling peringatan almuminun23 71 riwayat ayat diturunkan sehubungan niat abu jahal orang temannya berasal bani makhzum abu jahal bersumpah muhammad salat baitullah menjatuhkan batu kepalanya dilihatnya nabi sujud tangannya tersedia batu batu diangkatnya dilemparkan arah nabi sujud raguragu batu terlepas pegangan tangannya abu jahal kaumnya menceritakan bani makhzum tertarik cerita abu jahal melempar nabi beliau salat melaksanakan niat jahatnya allah membutakan matanya kaumnya buta menceritakan melaksanakan niatnya tibatiba muncul seekor binatang menerkamnya seandainya batu lemparkan binatang menerkamnya makna belenggu arti majazi kiasan belenggu penghalang menghalangi niat beriman allah digambarkan orangorang beriman memandang perbuatan jahat kerjakan menyebabkan sombong enggan mengikuti ajaran rasul pikirannya tertutup kebenaran manfaat pahami kecuali diwariskan nenek moyang ringkasnya penjara kebodohan seolaholah hati dipisahkan dinding berpikir merenungkan dalildalil kebenaran ajaran dibawa rasul mengartikan dinding menghalangi hijab allah menjadikan hijab menghalangi orangorang musyrik menyakiti rasul mata tertutup diartikan mengindra dilihatnya petunjuk meluruskan pikiran 10 ayat allah orangorang menerima petunjuk diancam siksaan pedih berubah hati terpatri mati menerima petunjuk disebabkan pikiran sanggup memikirkan kebenaran mata buta kebenaran ringkasnya ditetapkan allah kesesatannya bermanfaat baginya nasihat orang allah berfirman sesungguhnya orangorang kafir engkau muhammad peringatan engkau peringatan beriman allah mengunci hati pendengaran penglihatan tertutup azab berat albaqarah2 67 firmannya sungguh orangorang ketetapan tuhanmu beriman yunus10 96 ayat allah orangorang menerima petunjuk diancam siksaan pedih berubah hati terpatri mati menerima petunjuk disebabkan pikiran sanggup memikirkan kebenaran mata buta kebenaran ringkasnya ditetapkan allah kesesatannya bermanfaat baginya nasihat orang allah berfirman sesungguhnya orangorang kafir engkau muhammad peringatan engkau peringatan beriman allah mengunci hati pendengaran penglihatan tertutup azab berat albaqarah2 67 firmannya sungguh orangorang ketetapan tuhanmu beriman yunus10 96 ayat allah orang menerima petunjuk nabi muhammad takut mendengar ancaman allah orangorang beriman alquran melaksanakan pedoman digariskannya sadar gentar ngeri mendengar ancaman siksaan allah allah mahabesar rahmatnya mahapedih siksanya ayat kabarkanlah hambahambaku maha pengampun maha penyayang sesungguhnya azabku azab pedih alhijr15 4950 allah memerintahkan nabi muhammad kabar gembira orangorang beriman magfirah ampunan pahala mulia nikmat abadi dilukiskan mata terdengar telinga terlintas hati ayat sesungguhnya orangorang takut tuhannya memperoleh ampunan pahala almulk67 12 maksud firman allah takut tuhan maha pengasih melaksanakan perintah menjauhi larangannya orang bertakwa allah orang orangorang beriman berkepribadian ataslah allah kabar gembira nabi muhammad kabar gembira dosa kerjakan diampuni allah magfirahnya menikmati pahala mulia surga luasnya seluas langit bumi dinyatakan ayat bersegeralah mencari ampunan tuhanmu surga luasnya seluas langit bumi disediakan orangorang bertakwa ali imran3 133 orang takut tuhannya allah menghidupkan orang mati membangkitkan kuburnya masingmasing akhirat manusia memperoleh catatan perbuatan dunia tiada perbuatan luput catatan tertulis buku teliti alquran diletakkanlah kitab catatan amal engkau orang berdosa ketakutan tertulis dalamnya betapa celaka kitab tertinggal tercatat dapati kerjakan tertulis tuhanmu menzalimi jua alkahf18 49 perbuatan tertulis buku amal tinggalkan diikuti dimanfaatkan orang meninggal dunia ilmu pengetahuan diajarkannya harta benda diwakafkan rumah sakit didirikannya kesehatan masyarakat perbuatan jahat ditinggalkan fitnah ditebarkannya mengakibatkan orang berselisih berpecahbelah ringkasnya perbuatan menimbulkan pengaruh bermanfaat menimbulkan mudarat tertulis buku ayat sejalan hadis rasulullah berbunyibarang tradisi kebiasaan memperoleh pahalanya pahala orang mengamalkannya meninggal dikurangi pahala barangsiapa tradisi kebiasaan buruk memikul dosanya dosa orang mengerjakannya meninggal dunia dikurangi dosa rasulullah membaca ayat wanaktubu maqaddamu wa atsarahum mencatat kerjakan bekasbekas tinggalkan riwayat albukhari abu musa alasyari sehubungan makna firman allah menuliskan kerjakan bekasbekas tinggalkan imam attirmidzi meriwayatkan kisah dimuat ibnu katsir tafsirnya diceritakan orangorang bani salamah tinggal pinggiran kota medinah betapa jauhnya kediaman masjid nabi berjamaah memperoleh keutamaan salat berjamaah berniat memindahkan rumah daerah masjid turunlah ayat rasulullah memanggil beliau bersabda niatmu ditulis pindah ibnu jarir aththabari meriwayatkan rumah orang anshar masjid rasulullah memindahkannya turunlah ayat membatalkan maksud barangkali mendorong orangorang bani salamah segolongan sahabat anshar memindahkan rumah hadis nabi saw salat berjamaah 27 kali lipat pahalanya dibanding salat rasulullah bersabda manusia pahalanya salat orang berjalan kaki orang menunggu salat mengerjakannya imam pahalanya orang salat tidur riwayat albukhari muslim abu musa perbuatan bani adam tertulis buku teliti bumi penjelasan ahli tafsir imamum mubin kitab induk nyata lauh mahfudh ayat diperkuat keterangan ayatayat berbunyi musa pengetahuan tuhanku kitab lauh mahfudh tuhanku salah lupa thaha20 52 ayat tertulis alqamar54 53 penjelasan ayatayat datangnya kiamat manusia menerima balasan usahanya jahat ayat dipahami kabar gembira ampunan surga orang takwa tuhan mengikuti petunjuk alquran ditetapkan allah kebangkitan allah memerintahkan nabi muhammad menceritakan kaum musyrik quraisy kaum mendustakan risalahnya riwayat ashhabul qaryah pengajaran intisari kisah mendustakan rasul mengalami nasib malang dialami ashhabul qaryah tafsir diterangkan ashhabul qaryah penduduk kota antakia arab anthakiyah menyebut penduduk kota dikenal utusan menyebut utusan isa penduduk negeri menyebut rasul diutus penduduk negeri utusan bernama yuhana bulus berhasil melaksanakan misinya dikirim bernama syamun tugas risalah bawa penduduk antakia membersihkan perbuatan syirik melepaskan bentuk sesembahan allah ajaran tauhid ayat alasan mendasar kaumnya beriman allah kebanyakan orangorang mendustakan berkeyakinan ketiga utusan manusia keistimewaan menonjol dihargai kepandaian keahlian alasan tuhan maha pengasih menurunkan risalah kitab berisi wahyu memerintahkan beriman ketiga utusan menyimpulkan ketiga utusan bohong belaka firman allah menggambarkan penolakan ma anzala arrahman penduduk antakia mengenal tuhan mengingkarinya digantinya berhala rasul tolak pandangan dibantah utusanutusan allah benarbenar orang diutus penduduk bohong azab pedih menimpa tugas diridai allah kelak bersalah menanggung risiko kesalahan ayat rasul kepadamu diturunkan azab ditetapkan niscaya azab azab tibatiba menyadarinya alankabut29 53 ayat misi dibawa rasul risalah allah keputusan tangan manusia beriman risalah beriman faedah keimanan kebahagiaan dunia akhirat orangorang kafir melaksanakan seruan rasul akibatnya menimpa ayat penduduk antakia mematahkan alasanalasan rasul mengancam kesengsaraan menimpa kelak disebabkan perbuatan ketiga orang rasul menghentikan dakwah siasia terpaksa merajamnya batu menjatuhkan siksaan pedih ketiga utusan menangkis perkataan seandainya penduduk antakia kelak terpaksa mengalami siksaan akibat perbuatan mempersekutukan allah perbuatan maksiat kesalahankesalahan ketiga utusan mengajak mentauhidkan allah mengikhlaskan beribadah tobat kesalahan rasul memperingatkan azab allah pedih mengajak mengesakan allah menyiksa rasul balasan rasul bangsa melampaui batas berpikir menetapkan putusan menyiksa merajam rasul menganggap buruk orangorang semestinya petunjuk ayat pengertiannya ayat kebaikan kemakmuran usaha ditimpa kesusahan lemparkan kesialan musa pengikutnya ketahuilah sesungguhnya nasib tangan allah kebanyakan alaraf7 131 ayat penduduk antakia mematahkan alasanalasan rasul mengancam kesengsaraan menimpa kelak disebabkan perbuatan ketiga orang rasul menghentikan dakwah siasia terpaksa merajamnya batu menjatuhkan siksaan pedih ketiga utusan menangkis perkataan seandainya penduduk antakia kelak terpaksa mengalami siksaan akibat perbuatan mempersekutukan allah perbuatan maksiat kesalahankesalahan ketiga utusan mengajak mentauhidkan allah mengikhlaskan beribadah tobat kesalahan rasul memperingatkan azab allah pedih mengajak mengesakan allah menyiksa rasul balasan rasul bangsa melampaui batas berpikir menetapkan putusan menyiksa merajam rasul menganggap buruk orangorang semestinya petunjuk ayat pengertiannya ayat kebaikan kemakmuran usaha ditimpa kesusahan lemparkan kesialan musa pengikutnya ketahuilah sesungguhnya nasib tangan allah kebanyakan alaraf7 131 ayat sunatullah berlaku rasul bertugas kebenaran terdesak bantuan allah berkaitan kisah penolakan penduduk antakia utusan nabi isa datanglah lakilaki bernama habib annajjar memiliki pengaruh kekuasaan menentukan keluarga orang berpengaruh raja negeri dinamika kekuatan imannya pelosok negeri membela ketiga utusan memperingatkan orangorang menyiksa menyerukan penduduk kota mengikuti rasul petunjuk allah lakilaki ketiga utusan mendakwahkan kebenaran mengharapkan balas jasa jerih payahnya risalah memperoleh petunjuk allah disembah allah maha esa menyekutukannya lakilaki bernama habib annajjar penduduk antakia pelajaran pengajaran disampaikannya menyembah allah maha esa menciptakannya hidup sanalah menerima ganjaran perbuatan orang berbuat menikmati hasil kebaikannya berbuat jahat barang sanggup melepaskan azab balasannya penegasan kaumnya beriman habib mencari tuhan tuhan maha esa tuhan puja tuhan sanggup manfaat menolak mudarat mendengar pertolongan syafaat tuhantuhan barang menghindarkan azab allah menyembahnya menyembah sembah tuhan maha esa sungguh menempuh jalan sesat menyembah patung terbuat batu makhlukmakhluk manfaat menolak mudarat kesesatan lakilaki nasihatnya hadapan kaumnya ketiga utusan pendiriannya sejati dengarlah utusanutusan nabi isa beriman tuhanmu mengutus saksikanlah dengarkanlah ucapkan riwayat habib mengumandangkan pendiriannya kaum kafir melemparinya batu sekujur tubuhnya mengeluarkan darah habib meninggal syahid menegakkan kebenaran riwayat kakinya ditarik arah berlawanan sobek arah duburnya memancar darah segar gugur melaksanakan tugasnya menemui ajalnya pahlawan berdoa allah ya allah tunjukilah kaumku sesungguhnya orangorang kebangkitan allah memerintahkan habib masuklah engkau surga balasan engkau kerjakan dunia masuk merasakan betapa indah nikmatnya balasan allah orang beriman sabar melaksanakan tugas dakwah kaumku memperoleh ampunan kemuliaan allah magfirah kemuliaan dinikmati manusia beriman sesungguhnya ayat memakai tamanni mengharapkan dicapai mendorong kaum antakia orangorang mukmin berusaha memperoleh ganjaran tobat kekufuran masuk kelompok orang merasakan indahnya beriman allah menaati jalan wali allah menahan marah melimpahkan kasih sayang orang memusuhinya ibnu abbas habib menasihati kaumnya hidup ucapan ikutilah risalah dibawa utusan meninggal dunia akibat siksaan mengharapkan kaumku allah mengampuniku menjadikanku orangorang dimuliakan habib dibunuh allah menurunkan siksaannya jibril diperintahkan kaum durhaka kali teriakan halilintar kerasnya tibatiba mati balasan setimpal kesalahan mendustakan utusanutusan allah membunuh walinya mengingkari risalah allah ayat digambarkan kesadaran timbul hati cahaya iman menyinari jiwa orang berpendapat alasan baginya beriman allah menciptakan membentuknya rupa proses kejadian memeluk agama tauhid agama mengajarkan mempercayai allah tuhan maha esa ayat orang allah meninggalkan kehidupan dunia fana pernyataan timbul lubuk hatinya merasakan kekuasaan kebesaran allah menghambakan allah 1 merasakan kekuasaan kebesaran allah berhak disembah keyakinan menghambakan allah nikmat kesengsaraan kesenangan kesempitan kelapangan 2 hamba beribadah allah merasakan nikmat dianugerahkan tergantung nikmat allah 3 hamba mengharapkan pahala allah takut ditimpa siksanya hamba ayat hamba golongan hamba beribadah allah sesuai ditetapkannya ditimpa malapetaka kesengsaraan cobaancobaan jiwa raganya hidup matinya milik allah keimanan orang sesuai iman firman allah muhammad sesungguhnya salatku ibadahku hidupku matiku allah tuhan alamtidak sekutu baginya diperintahkan kepadaku orang pertamatama berserah muslim alanam6 162163 hamba patut menyembah tuhan allah maha esa seandainya menimpakan malapetaka kemudaratan diriku niscaya menolongku tuhantuhan sembah berdaya menyelamatkan kemudaratan malapetaka hamba patut menyembah tuhan allah maha esa seandainya menimpakan malapetaka kemudaratan diriku niscaya menolongku tuhantuhan sembah berdaya menyelamatkan kemudaratan malapetaka memperoleh patut baginya menghamba allah allah tuhan menyembah allah kesesatan nyata orang mengambil keputusan berdasar keyakinan penuh beriman allah tuhan kaumnya mengumumkan keimanan keyakinannya kaumnya sesungguhnya beriman allah tuhan dengarkanlah pernyataan imanku sikap pernyataan iman dilontarkan tengahtengah masyarakat bergelimang kekafiran kemusyrikan kemaksiatan benarbenar keberanian timbul cahaya iman menerangi hati nuraninya kaumnya beriman gentar ancaman membahayakan melaksanakan tugas suci mengajak umat jalan riwayat orang kaumnya menyerangnya membunuhnya membelanya qatadah kaumnya merajamnya batu berdoa tuhanku tunjukilah kaumku merajamnya mengembuskan napasnya penghabisan riwayat orang ayatayat bernama habib annajjar terkena penyakit campak suka bersedekah separuh penghasilannya seharihari disedekahkannya kaumnya mendengar pernyataan keimannya islam berkobarlah kemarahan membunuhnya mengembuskan napas turunlah malaikat memberitahukan allah mengampuni dosadosanya dilakukannya beriman dimasukkan surga golongan orangorang kemuliaan sisi allah detikdetik berisi harapan alangkah baiknya kaumku karunia allah dilimpahkannya kepadaku berkat keimananku memperoleh ampunan dosaku dimasukkan surga ganjaran berlipat ganda golongan orangorang memperoleh kemuliaan sisinya seandainya beriman pernyataan habib pernyataan nilainya ketinggian akhlaknya dirajam disiksa kaumnya berharap kaumnya sadar rahmat tuhan dialaminya orang mengambil keputusan berdasar keyakinan penuh beriman allah tuhan kaumnya mengumumkan keimanan keyakinannya kaumnya sesungguhnya beriman allah tuhan dengarkanlah pernyataan imanku sikap pernyataan iman dilontarkan tengahtengah masyarakat bergelimang kekafiran kemusyrikan kemaksiatan benarbenar keberanian timbul cahaya iman menerangi hati nuraninya kaumnya beriman gentar ancaman membahayakan melaksanakan tugas suci mengajak umat jalan riwayat orang kaumnya menyerangnya membunuhnya membelanya qatadah kaumnya merajamnya batu berdoa tuhanku tunjukilah kaumku merajamnya mengembuskan napasnya penghabisan riwayat orang ayatayat bernama habib annajjar terkena penyakit campak suka bersedekah separuh penghasilannya seharihari disedekahkannya kaumnya mendengar pernyataan keimannya islam berkobarlah kemarahan membunuhnya mengembuskan napas turunlah malaikat memberitahukan allah mengampuni dosadosanya dilakukannya beriman dimasukkan surga golongan orangorang kemuliaan sisi allah detikdetik berisi harapan alangkah baiknya kaumku karunia allah dilimpahkannya kepadaku berkat keimananku memperoleh ampunan dosaku dimasukkan surga ganjaran berlipat ganda golongan orangorang memperoleh kemuliaan sisinya seandainya beriman pernyataan habib pernyataan nilainya ketinggian akhlaknya dirajam disiksa kaumnya berharap kaumnya sadar rahmat tuhan dialaminya orang mengambil keputusan berdasar keyakinan penuh beriman allah tuhan kaumnya mengumumkan keimanan keyakinannya kaumnya sesungguhnya beriman allah tuhan dengarkanlah pernyataan imanku sikap pernyataan iman dilontarkan tengahtengah masyarakat bergelimang kekafiran kemusyrikan kemaksiatan benarbenar keberanian timbul cahaya iman menerangi hati nuraninya kaumnya beriman gentar ancaman membahayakan melaksanakan tugas suci mengajak umat jalan riwayat orang kaumnya menyerangnya membunuhnya membelanya qatadah kaumnya merajamnya batu berdoa tuhanku tunjukilah kaumku merajamnya mengembuskan napasnya penghabisan riwayat orang ayatayat bernama habib annajjar terkena penyakit campak suka bersedekah separuh penghasilannya seharihari disedekahkannya kaumnya mendengar pernyataan keimannya islam berkobarlah kemarahan membunuhnya mengembuskan napas turunlah malaikat memberitahukan allah mengampuni dosadosanya dilakukannya beriman dimasukkan surga golongan orangorang kemuliaan sisi allah detikdetik berisi harapan alangkah baiknya kaumku karunia allah dilimpahkannya kepadaku berkat keimananku memperoleh ampunan dosaku dimasukkan surga ganjaran berlipat ganda golongan orangorang memperoleh kemuliaan sisinya seandainya beriman pernyataan habib pernyataan nilainya ketinggian akhlaknya dirajam disiksa kaumnya berharap kaumnya sadar rahmat tuhan dialaminya ayat allah menerangkan azab ditimpakan kaum musyrik kafir mendustakan agamanya allah menurunkan pasukanpasukan malaikat membinasakan teriakan malaikat jibril orangorang kafir kaku bernyawa peristiwa cepatnya bukti betapa besarnya kekuasaan allah allah menerangkan sikap tingkah laku kaum kafir disesalkan menolak seruan iman memperolokolokkan rasul orangorang beriman jarang menganiaya membunuhnya berpikir akal sehat menerima seruan iman rasul orangorang beriman allah menerangkan kedudukan orangorang kafir akhirat tatkala ditimpa azab dahsyat mendustakan rasul allah memperingatkan memperhatikan nasib menimpa kaum kafir berabadabad ditimpa kemurkaan allah hancurlebur lenyap muka bumi takkan muncul dunia ibnu katsir kebanyakan ulama salaf meriwayatkan negeri ayat negeri antakiyah diutus utusan nabi isa negeri risalahnya keberatan menerima riwayat faktorfaktor 1tidak allah menghancurkan negeri antakiyah penduduk negeri penduduk negeri kali beriman isa allah menghancurkan negeri penduduknya beriman memenuhi seruan rasul diutus 2dalam ayat diterangkan negeri dihancurkan allah negeri penduduknya musnah alquran menerangkan allah menurunkan azab orangorang kafir kehancuran kemusnahan negerinya kitab taurat diturunkan kitab taurat diturunkan allah menurunkan azab dipahami firmannya sungguh musa kitab taurat binasakan umatumat pelita manusia petunjuk rahmat pelajaran alqashash28 43 3tidak nash kuat sehubungan riwayat keterangan menerangkan dimana peristiwa kaum muslimin percaya kisahkisah alquran kisah alquran terperinci kisahkisah diterangkan terperinci tiaptiap kisah maksud tujuannya kaum muslimin perincian kisah ayat kaum muslimin menjadikan kisahkisah pelajaran iktibar menambah menguatkan iman masingmasing ayat allah dikumpulkan hadiratnya mempertanggungjawabkan perbuatan tingkah laku dunia ayat diterangkan salah tandatanda kekuasaan allah kebangkitan tanah mati tandus gersang menumbuhkan tanaman kekuasaan allah hidup turunnya hujan langit tumbuhnya bermacammacam tanaman menghasilkan bahan makanan manusia makhluk hidup bumi manusia makhluk memperoleh makanan menumbuhkan jasmani kekuatan samping hasilhasil bumi dijadikan bahan perniagaan diperdagangkan manusia allah menciptakan bumi kebun ladang sawah ditanami bermacammacam tanaman menghasilkan bahan makanan manusia korma anggur bahan makanan bangsa arab padi gandum jagung makanan pokok bangsabangsa samping allah menciptakan sumbersumber air mengalir sungaisungai kehidupan bumi air minum mandi mencuci irigasi pembangkit tenaga listrik memajukan pertanian industri allah menciptakan menganugerahkan manusia memperoleh makanan buah hasilnya hasil usaha kerajinan tangan kenal hasilhasil pertanian industri terhitung memikirkan betapa besarnya kekuasaan nikmat allah bersyukur sikap tingkah laku sungguh layak orangorang berakal ayat diterangkan bukti kekuasaan allah menciptakan makhluknya berpasangpasangan pasangan jenis lelaki perempuan berpasangan sifat kuat lemah rendah kaya miskin perpasangan arus listrik arus positif negatif menimbulkan kekuatan membangkitkan tenaga listrik menimbulkan cahaya tenaga listrik cahaya dihasilkan vital kehidupan manusia zaman modern halhal berhasil manusia perpasangan dijangkau pengetahuan penemuan manusia kemajuan ilmu pengetahuan teknologi manusia menyingkapkan rahasiarahasia tersimpan perpasangan bidangbidang ayat diterangkan tandatanda kekuasaan kebesaran allah pasanganpasangan diciptakannya 1 bendabenda ditumbuhkannya bumi manusia tumbuhtumbuhan 2 jenis lakilaki jenis perempuan hubungan jenis lahirlah keturunanketurunan 3 halhal manusia ilmu allah luas terhingga manusia pasangan halhal terungkap manusia ayat allah bukti kekuasaannya mahabesar bukti kebangkitan malam allah menanggalkan siang malam tibatiba manusia kegelapan ayat meletakkan dasardasar ilmu pengetahuan alam ilmu falak siang malam bergeraknya tata surya bumi matahari muka bumi terkena cahaya matahari mengalami siang terkena cahaya matahari mengalami malam silih berganti kemajuan ilmu pengetahuan manusia ilmu falak astronomi bendabenda angkasa raya kemajuan teknologi manusia mengarungi ruang angkasa mengamatinya bumi siang malam berfaedah manusia siang keperluan hidup malam beristirahat tidur salah kebutuhan jasmaniah rohaniah allah bukti kekuasaannya peredaran matahari bergerak garis edarnya tertib ketentuan ditetapkan allah menyimpang garis ditentukan andaikata menyimpang seujung rambut niscaya tabrakan bendabenda langit membayangkan akibat peristiwa sepintas orang menerima matahari bergerak bumi tempatnya pagi matahari sebelah timur sore barat ilmu falak matahari berjalan berputar sumbunya bumi depannya berjalan berputar sumbunya beredar mengelilingi matahari ditetapkan ilmu falak sejalan diterangkan ayat kemampuan ilmu pengetahuan teknologi manusia terbuka kebenarankebenaran dikemukakan alquran belas abad allahu akbar allah mahabesar kekuasaannya allah menetapkan jarakjarak peredaran jarak mengalami perubahan bentuk ukurannya kekuatan sinarnya mulamula timbul cahaya lemah sabit bentuk melengkung sinar terang bentuknya sempurna bundarnya purnama cahaya terang menyusut menyerupai tandan kering berbentuk melengkung cahaya pudar diperhatikan bendabenda angkasa bermiliarmiliar banyaknya jarak berbedabeda kecepatan gerak berjalan teratur rapi menambah keyakinan terbatasnya ruang alam betapa besarnya kekuasaan allah menciptakan mengatur makhluknya memperhatikan katakata mulut orang beriman ucapan allahu akbar allah mahabesar mahabesar kekuasaannya berdasarkan pengaturan ketetapan allah berlaku bendabenda alam peraturan sunnatullah tabrakan matahari malam mendahului siang berjalan sesuai peraturan ditetapkannya masingmasing bergerak garis edarnya ditetapkan allah untuknya betapa kecilnya kekuasaan manusia dibanding kekuasaan allah menciptakan mengatur perjalanan bendabenda alam berjalan tertib manusia bermacammacam peraturan lintas jalan raya dilengkapi ramburambu beraneka ragam kecelakaan lalulintas jalan raya manamana peraturan manusia sisi kelemahannya ayat allah mengemukakan kapal berlayar samudera salah bukti kebesaran kekuasaannya kapal mengangkut manusia barangbarang keperluannya negeri negeri berdekatan letaknya berjauhan penggunaan alatalat angkutan laut salah sarana perhubungan dimanfaatkan manusia bergerak mengangkut barang dikenal zaman dikenal zaman nabi nuh orang mulamula kapal nabi nuh kapal perintah bimbingan allah diterangkan firmannya buatlah kapal pengawasan petunjuk wahyu hud11 37 perahu sampan kapal berbobot berat digerakkan tenaga manusia kekuatan angin tenaga mesin meluncur mudah air mengangkut manusia barang pulau pulau benua benua terkait kekuatan menahan kapal tenggelam buktibukti kekuasaan kebesaran allah pemberlakuan hukum alamnya allah berfirman engkau memperhatikan sesungguhnya kapal berlayar laut nikmat allah diperlihatkannya kepadamu tandatanda kebesarannya sungguh tandatanda kebesarannya orang sabar bersyukur luqman31 31 ayat allah manusia bukti kekuasaannya allah manusia bermacammacam kendaraan perahu bahtera kapal hewanhewan dijadikan kendaraan alat angkutan kuda keledai unta gajah alat angkutan darat manusia ayat allah berfirman menciptakan kuda bagal keledai tunggangi perhiasan allah menciptakan ketahui annahl16 8 pengangkutan orang barangbarang manusia alatalat angkutan darat ditarik hewanhewan dokar pedati gerobak akal dikaruniakan allah manusia alat angkutan bergerak tenaga mesin memakai bahan bakar minyak bumi batu bara disediakan dikaruniakan allah manusia kendaraan bermesin berjalan cepat bermuatan berkat kemajuan akal nalar ilmu pengetahuan dikaruniakan allah manusia kendaraankendaraan terbang udara balon pesawat terbang roketroket menggerakkan kapalkapal ruang angkasa kecepatannya melebihi kecepatan suara nikmat allah manusia menyiasati hukum gravitasi manusia berhasil menciptakan pesawat terbang kepentingan transportasi manusia allah memperingatkan menenggelamkan kapalkapal berlayar lautan niscaya datangnya angin badai kencang menimbulkan gelombanggelombang dahsyat menyebabkan kapalkapal tenggelam penumpangnya binasa terkubur dasar laut ditolong peringatan manusia sombong takabur prestasi menciptakan kendaraan berjalan darat laut udara sematamata kepandaian otaknya karunia allah ilmu alam terapung air berat jenis benda ringan berat jenis air dilaluinya ketentuan sunatullah ditetapkan allah air diciptakannya menyiasati hukum alam air benda tenggelam terapung manusia kapal selam menyelam dasar laut timbul permukaan air mengurangi udara rongga kapal selam tenggelam udara dipompakan rongganya kapal selam ringan terapung permukaan air ayat allah kasih sayangnya hambahambanya bersenangsenang menikmati karunianya allah membiarkan kendaraankendaraan binasa berjalan darat berlayar permukaan air terbang udara orangorang kendaraan takabur cermat berhatihati sewaktuwaktu kecelakaan bersangkutan berhatihati cermat lalai allah menerangkan andaikata orangorang ingkar dianjurkan menjaga siksaan allah berpaling mendengarkan anjuran anjuran rahmat allah menjaga siksaan allah bertakwa apaapa diperintahkannya menjauhi larangannya mensyukuri karunianya hati orangorang ingkar tertutup kebenaran senantiasa berpaling nasihatnasihat wajarlah ditimpa kemurkaan siksaan allah allah orangorang ingkar senantiasa memalingkan muka tandatanda keesaan kekuasaannya mengakui kerasulan utusannya hati buta mata kepala terang tandatanda allah sisi keingkaran keengganan menyumbangkan harta dikaruniakannya dianjurkan menafkahkan harta kepentingan fakir miskin orang bantuan orangorang beriman menganjurkan makan allah makan allah samping orangorang mukmin suka menyumbangkan harta benda membantu fakir miskin orangorang sesat bodoh alangkah pendapat kebenaran menyumbangkan harta benda menolong orang sumbangan wajib zakat sumbangan suka rela sedekah perwujudan iman syukur nikmat allah menghilangkan sifat bakhil jiwa manusia harta benda ajaran islam fungsi sosial kepentingan harta benda dijadikan alat mempererat tali persaudaraan solidaritas kegotongroyongan manusia hidup mengharapkan pertolongan orang keperluan hidup kaya raya sisi sifatsifat jelek kaum ingkar ketidakpercayaan kebangkitan mati kelak dibangkitkan mati mempertanggungjawabkan perbuatan dunia sikap mengejek janji terlaksana kaum ingkar hati terbuka menerima kebenaran penyesalan barulah timbul menghadapi kenyataan dulunya ingkari allah memperingatkan menunggu datangnya kebangkitan teriakan abaaba suara tiupan sangkakala membawa kehancuran alam manusia dibangkitkan dikumpulkan hadapan allah diperhitungkan perbuatannya selagi dunia menerima balasan sesuai perbuatan ayat maksudnya ayat firman allah menunggu kedatangan kiamat mendadak menyadarinya azzukhruf43 66 manusia menyadari kedatangan kiamat dimatikan tibatiba berselisih berbantahbantahan urusan dunia peristiwa kiamat kematian tibatiba hasil kompromi allah manusia kehendak kekuasaan allah diriwayatkan ibnu jarir aththabari ibnu umar sangkakala benarbenar ditiup manusia kesibukan urusan masingmasing jalan pasar orang tawarmenawar pakaian pakaian tangan salah tibatiba ditiupkan sangkakala mati bergelimpangan firman allah ayat diriwayatkan albukhari muslim abu hurairah ra rasulullah saw bersabda kiamat benarbenar orang menggelar pakaian tawarmenawar berjualbeli melipat kiamat benarbenar kolam minuman kolam kiamat benarbenar memeras susu kambingnya meminumnya kiamat benarbenar mengangkat makanan dimasukkannya mulutnya memakannya riwayat albukhari muslim abu hurairah cepat datangnya peristiwa tibatiba kesempatan berwasiat meninggalkan pesan keluarganya berkumpul masingmasing menghadapi persoalannya menunggu keputusan pengadilan tuhan mahaadil mahakuasa manusia mati tiupan sangkakala ditiuplah sangkakala membangkitkan kuburnya manusia bangkit hidup bangun bergegas menemui allah mahakuasa menerima hisab ayat berhubungan ayat firman allah kubur cepat seakanakan pergi berhalaberhala dunia almaarij70 43 ayat menerangkan keheranan kekagetan orangorang kafir dibangkitkan kubur aduhai celakalah membangkitkan tidur heran tercengang dibangkitkan alam kubur menghadapi malapetaka kesulitan heran tercengang orangorang beriman alami sesuai dijanjikan allah rasul utus dunia diberitahu janji ancaman kebangkitan hadapi heran tercengang alami riwayat bunyi sangkakala ayat suara malaikat israfil keras menyerukan tulangbelulang hancurlebur allah memerintahkan berkumpul menerima keputusan adil ayat orangorang kafir membangkitkan menghidupkan kebangkitan hidup dunia pengertian seakanakan allah menyuruh lakukan rasul diutus ayat menerangkan mudahnya allah membangkitkan manusia datangnya kiamat teriakan hiduplah manusia berkumpul hadapan allah menerima perhitungan keputusan adil darinya ayat maksudnya ayat firmannya urusan kejadian kiamat sekejap mata cepat sesungguhnya allah mahakuasa annahl16 77 firmannya pengembalian tiupan hidup bumi annaziat79 1314 allah menerangkan kiamat manusia menerima balasan perbuatan dilakukannya hidup dunia perbuatan dibalas pahala berlipat ganda perbuatan buruk jahat dibalas siksa seimbang perbuatan sifat allah keputusan adil keputusan adil menerima pahala kebaikan orang menerima azab perbuatan jahat orang allah menerangkan orangorang beriman dibalas allah pahala berlipat ganda surga penuh kenikmatan dalamnya merasakan kesenangan kenikmatan rasakan keindahan lihat suara menyejukkan kalbu dengar terpikir azab diderita orangorang kafir terbenam neraka dirasakan diingatnya kegembiraan kepuasan hati temantemannya surga surga orangorang beriman istriistri tamantaman indah pohon rindang duduk sofa tempattempat tidur berbincangbincang menikmati rezeki peroleh tuhan perkataan hum wa azwajuhum pasangan dipahami orangorang beriman tinggal pasangan bahagia damai surga memperoleh nikmat bentuk tiada taranya bentuk langsung nikmati memperoleh nyaman indah merasakan makanan lezat bentuk pemenuhan citacita anggota kepala keluarga hidup dunia mencitacitakan keluarga berbahagia istri cantik setia keinginankeinginan dipenuhi allah surga ayat diterangkan anak cucu beriman ditinggikan allah derajatnya derajat dikumpulkan orang tua surga membedabedakan pemberian nikmat masingmasing anggota keluarga allah berfirman orangorang beriman beserta anak cucu mengikuti keimanan pertemukan anak cucu surga mengurangi pahala amal kebajikan orang terikat dikerjakannya aththur52 21 ayat dipahami mukmin berusaha menjadikan suami istri anakanak keluarga orangorang beriman citacita berhubungan keluarga dikabulkan allah akhirat orangorang beriman memakan bermacammacam buahbuahan lezat surga memperoleh suka bermain disediakan alat permainan suka olahraga disediakan kebutuhan olahraga alat kesenian firman allah dalamnya buahbuahan aman tenteram addukhan44 55 58 salam allah memuliakan salam langsung allah perantaraan malaikat firman allah malaikat masuk tempattempat pintu selamat sejahtera atasmu kesabaranmu alangkah nikmatnya kesudahan arrad13 2324 salam selamat sejahtera terpelihara disenangi memperoleh diingini orang memperoleh kenikmatan jasmani rohani tiada bandingannya salam allah memuliakan salam langsung allah perantaraan malaikat firman allah aââsedang malaikat masuk tempattempat pintu selamat sejahtera atasmu kesabaranmu alangkah nikmatnya kesudahan arrad13 2324 salam selamat sejahtera terpelihara disenangi memperoleh diingini orang memperoleh kenikmatan jasmani rohani tiada bandingannya allah memerintahkan orangorang kafir berpisah orangorang beriman masuk neraka disediakan perintah allah manusia selesai dihisab padang mahsyar orangorang beriman diperintahkan masuk surga orangorang kafir diperintahkan masuk neraka ayat senada ayat firman allah diperintahkan malaikat kumpulkanlah orangorang zalim beserta teman sejawat sembah allah tunjukkanlah jalan neraka ashshaffat37 2223 ayat diterangkan orangorang kafir digiring masuk neraka dihardik allah perbuatanperbuatan dosa kerjakan dunia allah berfirman wasiatkan kepadamu sekalikali menyembah setan samping kemukakan kepadamu buktibukti kuat akal pikiran utus rasul kepadamu membawa kitab berisi petunjuk jalan kebahagiaan dunia akhirat hidayat pengutusan rasul alasan bagimu mengikuti godaan setan hiraukan nasibmu allah menerangkan alasannya melarang manusia mengikuti setan setan musuh nyata manusia permusuhan manusia setan setan menyesatkan adam hawa dikeluarkan allah surga setan berusaha berdaya upaya menyesatkan manusia allah memerintahkan manusia menyembahnya mengikuti diperintahkannya menghentikan dilarangnya melaksanakan diperintahkannya menghentikan dilarangnya menempuh jalan diridai jalan lurus agama berasal tuhan semesta alam ayat menerangkan pengaruh akibat godaan setan manusia ingkar menaati allah mempersekutukannya alangkah lemahnya hati manusia tergoda setan dianugerahi akal pikiran perasaan kemampuan jasmani rohani taufik hidayah agama rasul anugerah manusia membedakan salah jalan lurus jalan sesat perbuatan dosa amal saleh lalai memperturutkan hawa nafsunya allah orangorang kafir hai orangorang kafir neraka jahanam janjikan kepadamu janji rasul diutus kepadamu hidup dunia mempercayainya ingkar durhaka kepadaku menyembah tuhan selainku alquran hadzihi bentuk isim isyarah menggambarkan neraka jahanam hadapan gambaran mengerikan allah memerintahkan hai orangorang kafir masuklah rasakanlah panasnya api neraka tetaplah dalamnya balasan keingkaran perbuatan dosa kerjakan ayatayat dipahami seakanakan allah memperingatkan orangorang kafir diazab menyesal putus asa bersedih hati azab alami azab ketetapan tuhan diubah hidup dunia bermacammacam peringatan bermacammacam cobaan ingkar rasakanlah terimalah azab ditimpakan menerima azab neraka orangorang kafir mengingkari perbuatanperbuatan jahat dunia diterangkan firman allah bohong kecuali allah ya tuhan mempersekutukan allah alanam6 23 ayat 65 allah mengunci mati mulutmulut berbohong mendebat perbuatan tangantangan berbicara kakikaki saksi kerjakan mengelak perbuatanperbuatan melawan agama akhirat hukum berlaku seadiladilnya sesuai perbuatan dunia riwayat anas bin malik dikatakandari anas bin malik sisi nabi saw tibatiba beliau tertawa beliau tahukah tertawa allah rasulnya beliau berkatasaya tertawa pembicaraan hamba tuhannya hamba tuhanku engkau menyelamatkan kezaliman ya selamatkan tuhannya hamba sesungguhnya mengizinkan diriku kecuali saksi padaku tuhannya saksi dirimu malaikat pencatat amal saksi nabi saw mulut hamba ditutup anggotaanggota badan diperintahkan berbicara bicaralah nabi saw anggotaanggota badan berbicara sesuai perbuatannya riwayat imam abu yala almaushuli ayatayat alquran menerangkan persaksian anggota tubuh manusia perbuatanperbuatan lakukan hidup dunia firman allah lidah tangan kaki saksi kerjakan annur24 24 allah menjadikan tangan kaki berbicara saksi tanganlah perbuatan kaki menyaksikan tangan perbuatan tangan ikrar pengakuan perkataan kaki persaksian perbuatan buruk manusia dibukakan hidup dunia orang malu sukar menyembunyikan muka manusia membunuh sanggup menahan malu akhirat mengalami sanggup mengalami menanggungnya hidup dunia ayat menerangkan kekuasaan allah hambahambanya menghapus penglihatan pendengaran orangorang kafir beramal berbuat sifat kasih sayang allah manusia dilakukannya orangorang kafir berbuat dunia sesuai petunjuk agama lakukan berbuat dosa samping memiliki amal kebaikan pahala dosadosa siksaan allah akhirat berat mengelak kesaksian tangan kaki ayat menerangkan kekuasaan allah allah mengubah bentuk orangorang kafir sanggup berjalan allah maha pengasih maha penyayang orangorang kafir memiliki kesempatan beramal saleh sesuai petunjuk agama melakukannya bertambah ingkar siksa berat menghinakan akhirat allah barang dipanjangkan umurnya niscaya dikembali kejadiannya lemah akal anak kuat ibadahibadah berat lupa ibadah ayat allah mengerti kesempatan selagi muda kuat nabi saw menerangkan hadisnya berbunyi pergunakan kesempatan luangmu sibukmu kayamu miskinmu sehatmu sakitmu mudamu tuamu hidupmu matimuriwayat alhakim ibnu abbas orangorang kafir akalnya tua umur lemah jasmani rohaninya berbuat allah memberinya umur berbuat beramal saleh menuntut ilmu beribadah umur sebaikbaiknya allah mengutus rasul membawa petunjuk jalan lurus mengikuti rasul petunjuk mendustakan mengingkarinya ayat allah membantah tuduhan kaum kafir alquran syair diciptakan nabi muhammad saw tuduhan muhammad penyair dibantah keras ayat alquran wahyu allah membawa kebenaran nabi muhammad saw bertugas menyampaikannya umat manusia kebenaran diterima allah nabi muhammad penyair mengkhayal rasul allah membawa kebenaran memperbaiki orangorang jahiliah alquran berbeda syair berkembang tanah arab perbedaan 1syair arab rangkaian kalimatkalimat terikat wazan timbangan kalimat pola bahrbahr irama notasi syair arab bahr kamil bahr rajaz lainlain ayatayat alquran susunan kalimatnya indah pilihan diksi katakatanya terikat wazan bahr syair arab 2syair arab terikat qafiyah huruf dipenuhi rusaklah syair unsur pemaksaan takalluf ayatayat alquran huruf bersajak masju indah kaku unsur pemaksaan takalluf 3isi syair arab khayalan penyair imajinasi melupakan sesuai kenyataan ayatayat alquran sesuai kenyataan alam gaib alam nyata informasi 4syairsyair arab pujipujian berlebihlebihan raja kepala suku menjadikan raja bertambah sombong syair berisi celaan ejekan musuh meningkatkan permusuhan alquran berbicara kebenaran orang sombong ayat alquran melarang kesombongan kebencian permusuhan 5syairsyair arab seringkali disusun dirangkai penyair hadiah mata pencaharian penyair ayatayat alquran sematamata informasi petunjuk pelajaran ayat alquran diperjualbelikan harga murah memperoleh penghasilan halhal terbukti bahasa alquran indah syair kandungan isinya manfaat kehidupan manusia allah mengajarkan syair muhammad saw mewahyukan alquran umat manusia tuduhan kaum musyrik kaum kafir muhammad saw penyair tuduhan patut diterima akal sehat allah alquran muhammad saw pelajaran kitab suci penerangan umat manusia mencapai kebahagiaan lahir batin dunia akhirat kaum musyrik alquran syair katakata kalimatkalimat dalamnya indah kadangkadang alquran sihir katakata susunan kalimatnya memesona mendengarnya tuduhan alquran sihir syair syair susunan terikat polapola alquran allah fungsi alquran peringatan umat manusia samping menerangkan kepastian ketetapan azab orangorang kafir orangorang hati pikiran semangatnya hidup mengambil alquran pedoman utama alquran membawa ajaran melenyapkan kebodohan kebekuan menyembuhkan penyakitpenyakit mental merusak hidup manusia lahir batin rahmat orangorang bertakwa orangorang hati pikiran semangatnya mati membeku mengambil pelajaran bimbingan alquran godaan setan membelenggu rupa hati pemuka kaum kafir musyrik mengakui kebenaran kemukjizatan alquran berani mengemukakan pengakuan takut kehilangan pengaruh lingkungan kaumnya menyebabkan turunnya kewibawaan kehilangan sumber penghasilan allah memperingatkan kaum kafir sifat rahmat dikaruniakannya sepatutnya disyukuri rahmat dikaruniakan kuasai ambil manfaatnya rupa bersyukur mengingkari rahmat rahmat karunia allah bermacammacam hewan binatang ternak diciptakan disediakannya manusia hewan jadikan kendaraan mengangkut barangbarang hewan memperoleh bahan makanan minuman pakaian alatalat keperluan bersyukur allah menciptakan menyediakan kepentingan allah memperingatkan kaum kafir sifat rahmat dikaruniakannya sepatutnya disyukuri rahmat dikaruniakan kuasai ambil manfaatnya rupa bersyukur mengingkari rahmat rahmat karunia allah bermacammacam hewan binatang ternak diciptakan disediakannya manusia hewan jadikan kendaraan mengangkut barangbarang hewan memperoleh bahan makanan minuman pakaian alatalat keperluan bersyukur allah menciptakan menyediakan kepentingan allah memperingatkan kaum kafir sifat rahmat dikaruniakannya sepatutnya disyukuri rahmat dikaruniakan kuasai ambil manfaatnya rupa bersyukur mengingkari rahmat rahmat karunia allah bermacammacam hewan binatang ternak diciptakan disediakannya manusia hewan jadikan kendaraan mengangkut barangbarang hewan memperoleh bahan makanan minuman pakaian alatalat keperluan bersyukur allah menciptakan menyediakan kepentingan allah menerangkan ayat kaum kafir menguasai mengambil manfaat rupa rahmat diciptakan dikaruniakan allah bersyukur bertuhan allah menyangka pertolongan menyembah patung berhala benda pertolongan apaapa mengharapkan mustahil dibenarkan pikiran akal sehat allah menerangkan ayat kaum kafir menguasai mengambil manfaat rupa rahmat diciptakan dikaruniakan allah bersyukur bertuhan allah menyangka pertolongan menyembah patung berhala benda pertolongan apaapa mengharapkan mustahil dibenarkan pikiran akal sehat allah menghibur nabi muhammad saw tingkah laku perbuatan kaum kafir musyrik nabi sedih mendengarkan ucapan tuduhan bukanbukan alquran allah maha perbuatan terangterangan rahasiakan dimintakan pertanggungjawabannya kelak kiamat menerima balasannya azab pedih manusia percaya kebangkitan ayat allah kekuasaannya menciptakan manusia makhluknya dikemukakan nada keheranan sikap manusia manusia memikirkan memperhatikan allah menciptakannya setetes air mani proses lahir dunia bentuk manusia sempurna orang bersikap memusuhi allah rasulnya sikap benarbenar diterima pikiran sehat manusia menyadari allah kuasa menciptakannya setetes air mani menjadikan makhluk bumi allah kuasa mengembalikannya kejadiannya kuasa mengulangi penciptaannya membangkitkannya kehidupannya manusia bersikap melawan perintah allah ayat keraguan kaum kafir mekah kebangkitan berpendapat melupakan kejadian masingmasing allah menciptakan setetes air mani lahir berwujud manusia hidup utuh seandainya menyadari allah kuasa menghidupkannya mati tulangbelulang remuk ayat allah memerintahkan nabi muhammad saw orangorang menghidupkan tulangtulang lapuk manusia hidup utuh allah menciptakannya kali allah maha makhluk ciptaannya manusia mengulang perbuatan mudah melakukannya kali allah menciptakan kali mudahnya mengulanginya allah mahakuasa ayat allah memerintahkan rasulnya orangorang musyrik menghidupkan tulangtulang lapuk allah menciptakan api menyala kayu pohon basah hijau kayu kering menyalakan api kehidupan seharihari orang arab jenis kayu digesekkan memercikkan api diciptakan allah manusia menghangatkan badan memasak menggunakannya penerangan kebutuhan pemberian contoh seharihari kayu api tulangtulang lapuk dingin kering menerima kehidupan kehidupan panas seharihari menyaksikan kayu lapuk dingin menimbulkan panas menghidupkan api kayu basah berdaun menyalakan api kajian ilmiah api diinterpretasikan energi tumbuhan proses pemanfaatan energi matahari mengubah bahan diambil tumbuhan energi kimiawi penjelasan perubahan energi proses fotosintesa tumbuhan salah terpenting kloroplas chloroplast daun kloroplas ribuan kloropil chlorophyl butir hijau daun bahasa alquran dikenal nama alkhadir bahan hijau ayat menyinggung keberadaan kloropil berwarna hijau alanam6 99 peranan matahari menjalankan pabrik hijau attakwir81 1718 sel tumbuhan sel manusia binatang langsung energi matahari tumbuhan mengubah energi matahari energi kimia menyimpannya bentuk nutrien khusus proses dinamakan fotosintesis photosynthesis sel berwarna hijau mikroskop satusatunya laboratorium dunia menyimpan energi matahari bentuk bahan organik diuraikan tumbuhan makhluk kelangsungan kehidupan makhluk samping menghasilkan bahan makanan proses fotosintesa tumbuhan menghasilkan oksigen oksigen bahan bernapas makhluk hidup manusia binatang tepatlah allah contoh kayu kering menyalakan api kayu hijau basah dijadikan kayu api tulangtulang menerima kehidupan tulangtulang segar tulang lapuk menerima kehidupan kekuasaan allah allah mengemukakan orangorang mempercayai kebangkitan percaya allah kuasa menciptakan langit bumi allah kuasa menciptakan jawabannya allah kuasa menciptakannya maha pencipta maha allah menerangkan betapa mudah baginya menciptakan menciptakan makhluk allah berfirman sertamerta terwujudlah makhluk kekuasaannya kebangkitan manusia dihidupkannya kehancuran kiamat mustahil patut diingkari orangorang beriman allah mahasuci tangannya kekuasaan penuh alam menciptakan mengatur memeliharanya jualah makhluk dikembalikan pengakuan keyakinan timbul manusia pikiran sehat memperhatikan isi alam bukti kekuasaan allah",
        "top_frequencies": {
            "top_5": [
                [
                    "allah",
                    274
                ],
                [
                    "manusia",
                    102
                ],
                [
                    "ayat",
                    82
                ],
                [
                    "orangorang",
                    80
                ],
                [
                    "orang",
                    62
                ]
            ],
            "top_10": [
                [
                    "allah",
                    274
                ],
                [
                    "manusia",
                    102
                ],
                [
                    "ayat",
                    82
                ],
                [
                    "orangorang",
                    80
                ],
                [
                    "orang",
                    62
                ],
                [
                    "beriman",
                    53
                ],
                [
                    "alquran",
                    42
                ],
                [
                    "rasul",
                    41
                ],
                [
                    "kafir",
                    38
                ],
                [
                    "perbuatan",
                    33
                ]
            ],
            "top_15": [
                [
                    "allah",
                    274
                ],
                [
                    "manusia",
                    102
                ],
                [
                    "ayat",
                    82
                ],
                [
                    "orangorang",
                    80
                ],
                [
                    "orang",
                    62
                ],
                [
                    "beriman",
                    53
                ],
                [
                    "alquran",
                    42
                ],
                [
                    "rasul",
                    41
                ],
                [
                    "kafir",
                    38
                ],
                [
                    "perbuatan",
                    33
                ],
                [
                    "dunia",
                    32
                ],
                [
                    "kaumnya",
                    31
                ],
                [
                    "tuhan",
                    30
                ],
                [
                    "nabi",
                    28
                ],
                [
                    "memperoleh",
                    27
                ]
            ]
        }
    }
}